Files/__init__.py
Files/mainFile.py
HelloWorldTestProjectPyPi-0.0.1.dist-info/LICENSE
HelloWorldTestProjectPyPi-0.0.1.dist-info/METADATA
HelloWorldTestProjectPyPi-0.0.1.dist-info/WHEEL
HelloWorldTestProjectPyPi-0.0.1.dist-info/top_level.txt
HelloWorldTestProjectPyPi-0.0.1.dist-info/RECORD
