Metadata-Version: 2.1
Name: HelloWorldTestProjectPyPi
Version: 0.0.1
Summary: Just  Hello World Example Test Project
Home-page: UNKNOWN
Author: Charaf Eddine Chelloug
Author-email: <charaf@chelloug.com>
License: UNKNOWN
Keywords: python
Platform: UNKNOWN
Classifier: Development Status :: 1 - Planning
Classifier: Intended Audience :: Developers
Classifier: Programming Language :: Python :: 3
Classifier: Operating System :: Unix
Classifier: Operating System :: MacOS :: MacOS X
Classifier: Operating System :: Microsoft :: Windows
Requires-Dist: opencv-python
